{"id":"manager","pwd":"manager@@2020","name":"manager","phone":"01089596551","email":"manager@@2020"}
{"id":"jeong2020","pwd":"ebrwekr!#ed#23","name":"jeong2020","phone":"01098989888","email":"sd@sffasadd"}
{"id":"minsu99","pwd":"saddasdwe3@##$","name":"minsu","phone":"01089596551","email":"minsu@aaaaa"}
{"id":"chacha00","pwd":"chacha008@@","name":"chacha","phone":"01099998888","email":"chacha008@ssss"}
{"id":"selina2000","pwd":"nemo0408@@","name":"sumi","phone":"01089596551","email":"selina200@hgf"}
{"id":"minsu992","pwd":"saddasdwe3@##","name":"asd","phone":"01089596551","email":"asda@dsfsdd"}
